lapis_client_base/__init__.py
lapis_client_base/absent.py
lapis_client_base/api_base.py
lapis_client_base/params.py
lapis_client_base-0.2.2.dist-info/WHEEL
lapis_client_base-0.2.2.dist-info/METADATA
lapis_client_base-0.2.2.dist-info/RECORD
